coco_merge/__init__.py
coco_merge/__main__.py
coco_merge/cli.py
coco_merge/merger.py
yolococo/__init__.py
yolococo/__main__.py
yolococo/cli.py
yolococo/convert.py
yolococo-0.2.1.dist-info/licenses/LICENSE
yolococo-0.2.1.dist-info/METADATA
yolococo-0.2.1.dist-info/WHEEL
yolococo-0.2.1.dist-info/entry_points.txt
yolococo-0.2.1.dist-info/top_level.txt
yolococo-0.2.1.dist-info/RECORD
