Metadata-Version: 2.4
Name: yolococo
Version: 0.2.1
Summary: YOLO <-> COCO conversion tools with COCO dataset merging
License: MIT License
Keywords: yolo,coco,detection,dataset,conversion,merge,annotation
Classifier: Programming Language :: Python :: 3
Classifier: Programming Language :: Python :: 3.9
Classifier: License :: OSI Approved :: MIT License
Classifier: Operating System :: OS Independent
Classifier: Intended Audience :: Developers
Classifier: Topic :: Scientific/Engineering :: Artificial Intelligence
Classifier: Topic :: Multimedia :: Graphics
Classifier: Environment :: Console
Requires-Python: >=3.9
License-File: LICENSE
Requires-Dist: Pillow>=9.0
Requires-Dist: tqdm>=4.64
Provides-Extra: test
Requires-Dist: pytest>=7.0; extra == "test"
Dynamic: license-file
